LICENSE
MANIFEST.in
README.md
requirements.txt
setup.cfg
setup.py
llmrush/__init__.py
llmrush.egg-info/PKG-INFO
llmrush.egg-info/SOURCES.txt
llmrush.egg-info/dependency_links.txt
llmrush.egg-info/top_level.txt