Metadata-Version: 2.1
Name: llmrush
Version: 0.0.2
Summary: LlmRush: A Python package for training and Inference language models
Home-page: https://github.com/kadirnar/llmrush
Author: kadirnar
Author-email: kadir.nar@hotmail.com
License: Apache License 2.0
Platform: UNKNOWN
License-File: LICENSE
